{
  "asin": "B0GGRFL4C2",
  "url": "https://www.amazon.co.jp/dp/B0GGRFL4C2",
  "scraped_at": "2026-04-26T11:59:51.228968",
  "title": "[ミキハウス] 9分丈パンツ パンツ ロゴ 無地 男の子 女の子 ベビー キッズ 子供服 ズボン 12-3207-797",
  "brand": "MIKIHOUSE(ミキハウス)",
  "price": "￥1,480",
  "availability": "",
  "image_count": 24,
  "color_options": [
    {
      "name": "インディゴブルー",
      "asin": "",
      "selected": false,
      "thumbnail": "https://m.media-amazon.com/images/I/417KUmj05-L._SS64_.jpg",
      "image": "https://m.media-amazon.com/images/I/417KUmj05-L._SL1500_.jpg"
    },
    {
      "name": "ベージュ",
      "asin": "",
      "selected": false,
      "thumbnail": "https://m.media-amazon.com/images/I/4167i18iZZL._SS64_.jpg",
      "image": "https://m.media-amazon.com/images/I/4167i18iZZL._SL1500_.jpg"
    }
  ],
  "size_options": [
    {
      "name": "80",
      "available": true
    },
    {
      "name": "90",
      "available": true
    },
    {
      "name": "100",
      "available": true
    },
    {
      "name": "110",
      "available": true
    },
    {
      "name": "120",
      "available": true
    },
    {
      "name": "130",
      "available": true
    }
  ],
  "specs": {},
  "variant_images": {
    "インディゴブルー": [
      "https://m.media-amazon.com/images/I/417KUmj05-L._AC_SL1500_.jpg",
      "https://m.media-amazon.com/images/I/41PwpDVvNDL._AC_SL1500_.jpg",
      "https://m.media-amazon.com/images/I/71hCE7re0kL._AC_SL1500_.jpg",
      "https://m.media-amazon.com/images/I/61k+yQ9GZSL._AC_SL1500_.jpg",
      "https://m.media-amazon.com/images/I/61C-d2cg5VL._AC_SL1500_.jpg",
      "https://m.media-amazon.com/images/I/51LX-Z+B3TL._AC_SL1500_.jpg",
      "https://m.media-amazon.com/images/I/511Hfu1X3UL._AC_SL1500_.jpg"
    ],
    "ベージュ": [
      "https://m.media-amazon.com/images/I/4167i18iZZL._AC_SL1500_.jpg",
      "https://m.media-amazon.com/images/I/51RCVBPZDFL._AC_SL1500_.jpg",
      "https://m.media-amazon.com/images/I/31EWVyynYvL._AC_SL1500_.jpg",
      "https://m.media-amazon.com/images/I/51Wp393MBKL._AC_SL1500_.jpg",
      "https://m.media-amazon.com/images/I/51GlkoLVdrL._AC_SL1500_.jpg",
      "https://m.media-amazon.com/images/I/51Kkv6F4pkL._AC_SL1500_.jpg",
      "https://m.media-amazon.com/images/I/51854gb6SXL._AC_SL1500_.jpg"
    ]
  },
  "description": {
    "main": "小ぶりなレトロ ロゴ 刺繍が ポケット 部分に施された シンプル な ミキハウス 9分丈 パンツ です。 インディゴブルー はコーディネートが組みやすい ストレッチ デニム 素材の パンツ 、 ベージュ はポリエステルで 吸汗速乾 機能がついた パンツ になります。色によって使い分けていただける ミキハウス パンツ です。 夏 の普段着におすすめの mikihouse パンツ です。・ウエストはゴムのアジャスター付きで調節可能・ポケット：あり（前両サイド、後ろ右側）仕様: ９分丈 ● ベージュ のみ 吸汗速乾 素材使用",
    "aplus_text": "ブランド紹介\n子どもと家族の毎日を笑顔でいっぱいに\nPrevious page\nおすすめアイテム\n\nストアにアクセス\n\nミキハウスロゴグッズ\n\n人気のミキハウスロゴシリーズの雑貨\n\nカラバリ豊富に、コーディネートのポイントに\n\n私たちミキハウスは、\n\n子どものことを考えた\n\nものづくりとサービスをとおして、\n\n子どもを笑顔にし、家族を笑顔にし、\n\n妊娠・出産・子育ての毎日が\n\nハッピーになるお手伝いをしてまいります。\n\nNext page",
    "aplus_images": [
      "https://m.media-amazon.com/images/S/aplus-media-library-service-media/f91690ff-3e9b-4fbd-ad16-74a7add74b87.__CR0,0,1464,625_PT0_SX1464_V1___.jpg",
      "https://m.media-amazon.com/images/I/31MOY4p47LL.__AC_SR166,182___.jpg",
      "https://m.media-amazon.com/images/I/31nz6-AeaeL.__AC_SR166,182___.jpg",
      "https://m.media-amazon.com/images/I/31n7v5G1TFL.__AC_SR166,182___.jpg",
      "https://m.media-amazon.com/images/I/31Wnm%2BteLuL.__AC_SR166,182___.jpg",
      "https://m.media-amazon.com/images/S/aplus-media-library-service-media/6c3c2e46-0e0e-41e5-9c51-f669210bceef.__CR0,0,362,453_PT0_SX362_V1___.jpg",
      "https://m.media-amazon.com/images/S/aplus-media-library-service-media/5149c3d7-56dd-46e5-96d2-de78d23fc12b.__CR0,0,315,145_PT0_SX315_V1___.jpg"
    ],
    "brand_story": "ブランド紹介\n子どもと家族の毎日を笑顔でいっぱいに\nPrevious page\nおすすめアイテム\n\nストアにアクセス\n\nミキハウスロゴグッズ\n\n人気のミキハウスロゴシリーズの雑貨\n\nカラバリ豊富に、コーディネートのポイントに\n\n私たちミキハウスは、\n\n子どものことを考えた\n\nものづくりとサービスをとおして、\n\n子どもを笑顔にし、家族を笑顔にし、\n\n妊娠・出産・子育ての毎日が\n\nハッピーになるお手伝いをしてまいります。\n\nNext page"
  },
  "all_image_urls": [
    "https://m.media-amazon.com/images/I/51LX-Z+B3TL._AC_SR38,50_.jpg",
    "https://m.media-amazon.com/images/I/A1wOkmJotGL._AC_SL1500_.jpg",
    "https://m.media-amazon.com/images/I/911gJW+wUeL._AC_SL1500_.jpg",
    "https://m.media-amazon.com/images/I/511Hfu1X3UL._AC_SR38,50_.jpg",
    "https://m.media-amazon.com/images/I/51LX-Z+B3TL._AC_.jpg",
    "https://m.media-amazon.com/images/I/41PwpDVvNDL._AC_.jpg",
    "https://m.media-amazon.com/images/I/4167i18iZZL._AC_.jpg",
    "https://m.media-amazon.com/images/I/61C-d2cg5VL._AC_.jpg",
    "https://m.media-amazon.com/images/I/91IALhNAyXL._AC_SL1500_.jpg",
    "https://m.media-amazon.com/images/I/71hCE7re0kL._AC_SR38,50_.jpg",
    "https://m.media-amazon.com/images/I/A1QERYnOoSL._AC_SL1500_.jpg",
    "https://m.media-amazon.com/images/I/511Hfu1X3UL._AC_.jpg",
    "https://m.media-amazon.com/images/I/71hCE7re0kL._AC_.jpg",
    "https://m.media-amazon.com/images/I/41PwpDVvNDL._AC_SR38,50_.jpg",
    "https://m.media-amazon.com/images/I/51+iOYzyTaL._AC_.jpg",
    "https://m.media-amazon.com/images/I/417KUmj05-L._AC_.jpg",
    "https://m.media-amazon.com/images/I/61pdf3yk4UL._AC_SL1200_.jpg",
    "https://m.media-amazon.com/images/I/91Om6ASHCaL._AC_SL1500_.jpg",
    "https://m.media-amazon.com/images/I/61k+yQ9GZSL._AC_.jpg",
    "https://m.media-amazon.com/images/I/81OBcoav8eL._AC_SL1500_.jpg",
    "https://m.media-amazon.com/images/I/417KUmj05-L._AC_SR38,50_.jpg",
    "https://m.media-amazon.com/images/I/61k+yQ9GZSL._AC_SR38,50_.jpg",
    "https://m.media-amazon.com/images/I/91Y6kGau1AL._AC_SL1500_.jpg",
    "https://m.media-amazon.com/images/I/61C-d2cg5VL._AC_SR38,50_.jpg",
    "https://m.media-amazon.com/images/I/417KUmj05-L._AC_SL1500_.jpg",
    "https://m.media-amazon.com/images/I/41PwpDVvNDL._AC_SL1500_.jpg",
    "https://m.media-amazon.com/images/I/71hCE7re0kL._AC_SL1500_.jpg",
    "https://m.media-amazon.com/images/I/61k+yQ9GZSL._AC_SL1500_.jpg",
    "https://m.media-amazon.com/images/I/61C-d2cg5VL._AC_SL1500_.jpg",
    "https://m.media-amazon.com/images/I/51LX-Z+B3TL._AC_SL1500_.jpg",
    "https://m.media-amazon.com/images/I/511Hfu1X3UL._AC_SL1500_.jpg",
    "https://m.media-amazon.com/images/I/4167i18iZZL._AC_SL1500_.jpg",
    "https://m.media-amazon.com/images/I/51RCVBPZDFL._AC_SL1500_.jpg",
    "https://m.media-amazon.com/images/I/31EWVyynYvL._AC_SL1500_.jpg",
    "https://m.media-amazon.com/images/I/51Wp393MBKL._AC_SL1500_.jpg",
    "https://m.media-amazon.com/images/I/51GlkoLVdrL._AC_SL1500_.jpg",
    "https://m.media-amazon.com/images/I/51Kkv6F4pkL._AC_SL1500_.jpg",
    "https://m.media-amazon.com/images/I/51854gb6SXL._AC_SL1500_.jpg",
    "https://m.media-amazon.com/images/S/aplus-media-library-service-media/f91690ff-3e9b-4fbd-ad16-74a7add74b87.__CR0,0,1464,625_PT0_SX1464_V1___.jpg",
    "https://m.media-amazon.com/images/I/31MOY4p47LL.__AC_SR166,182___.jpg",
    "https://m.media-amazon.com/images/I/31nz6-AeaeL.__AC_SR166,182___.jpg",
    "https://m.media-amazon.com/images/I/31n7v5G1TFL.__AC_SR166,182___.jpg",
    "https://m.media-amazon.com/images/I/31Wnm%2BteLuL.__AC_SR166,182___.jpg",
    "https://m.media-amazon.com/images/S/aplus-media-library-service-media/6c3c2e46-0e0e-41e5-9c51-f669210bceef.__CR0,0,362,453_PT0_SX362_V1___.jpg",
    "https://m.media-amazon.com/images/S/aplus-media-library-service-media/5149c3d7-56dd-46e5-96d2-de78d23fc12b.__CR0,0,315,145_PT0_SX315_V1___.jpg"
  ],
  "title_kr": "[미키하우스] 9分丈팬츠 팬츠 로고 無地 남아 여아 베이비 키즈 아동복 ズボン 12-3207-797",
  "folder_name": "[미키하우스]_9分丈팬츠_팬츠_로고_無地_남아_여아_베이비_키즈_아동복_ズボン_12-3207-797"
}