{
  "asin": "B0GQDYF5DD",
  "url": "https://www.amazon.co.jp/dp/B0GQDYF5DD",
  "scraped_at": "2026-04-25T22:28:32.768995",
  "title": "[ミキハウス] WEB限定 ボーダー半袖Ｔシャツ ロゴ 男の子 女の子 ベビー キッズ 子供服 通園 通学 10-5262-147",
  "brand": "MIKIHOUSE(ミキハウス)",
  "price": "￥1,522",
  "rating": "5つ星のうち5.0",
  "review_count": "(1)",
  "availability": "",
  "image_count": 15,
  "color_options": [
    {
      "name": "ブラック/ホワイト",
      "asin": "",
      "selected": false,
      "thumbnail": "https://m.media-amazon.com/images/I/41cOYs9JoXL._SS64_.jpg",
      "image": "https://m.media-amazon.com/images/I/41cOYs9JoXL._SL1500_.jpg"
    },
    {
      "name": "グレー",
      "asin": "",
      "selected": false,
      "thumbnail": "https://m.media-amazon.com/images/I/31lIdNNYmVL._SS64_.jpg",
      "image": "https://m.media-amazon.com/images/I/31lIdNNYmVL._SL1500_.jpg"
    },
    {
      "name": "マルチカラー",
      "asin": "",
      "selected": false,
      "thumbnail": "https://m.media-amazon.com/images/I/41Di-sP4PZL._SS64_.jpg",
      "image": "https://m.media-amazon.com/images/I/41Di-sP4PZL._SL1500_.jpg"
    },
    {
      "name": "赤×紺",
      "asin": "",
      "selected": false,
      "thumbnail": "https://m.media-amazon.com/images/I/41lWh+B11dL._SS64_.jpg",
      "image": "https://m.media-amazon.com/images/I/41lWh+B11dL._SL1500_.jpg"
    }
  ],
  "size_options": [
    {
      "name": "80",
      "available": true
    },
    {
      "name": "90",
      "available": true
    },
    {
      "name": "100",
      "available": true
    },
    {
      "name": "110",
      "available": true
    },
    {
      "name": "120",
      "available": true
    },
    {
      "name": "130",
      "available": true
    },
    {
      "name": "140",
      "available": true
    },
    {
      "name": "150",
      "available": true
    }
  ],
  "specs": {
    "Amazon 売れ筋ランキング": "ボーイズ T シャツ - 49位",
    "カスタマーレビュー": "5.0 \n5つ星のうち5.0"
  },
  "variant_images": {
    "ブラック/ホワイト": [
      "https://m.media-amazon.com/images/I/41cOYs9JoXL._AC_SL1500_.jpg",
      "https://m.media-amazon.com/images/I/41qTsTRrCXL._AC_SL1500_.jpg",
      "https://m.media-amazon.com/images/I/51zJdh7QFJL._AC_SL1500_.jpg"
    ],
    "グレー": [
      "https://m.media-amazon.com/images/I/31lIdNNYmVL._AC_SL1500_.jpg",
      "https://m.media-amazon.com/images/I/31RrYoj1i1L._AC_SL1500_.jpg",
      "https://m.media-amazon.com/images/I/51MP0rmQOIL._AC_SL1500_.jpg"
    ],
    "マルチカラー": [
      "https://m.media-amazon.com/images/I/41Di-sP4PZL._AC_SL1500_.jpg",
      "https://m.media-amazon.com/images/I/412fMr4FznL._AC_SL1500_.jpg",
      "https://m.media-amazon.com/images/I/61zLAuYNrUL._AC_SL1500_.jpg"
    ],
    "赤×紺": [
      "https://m.media-amazon.com/images/I/41lWh+B11dL._AC_SL1500_.jpg",
      "https://m.media-amazon.com/images/I/41786CbvPyL._AC_SL1500_.jpg",
      "https://m.media-amazon.com/images/I/51EFF+EmBNL._AC_SL1500_.jpg"
    ]
  },
  "description": {
    "main": "「毎日着たい！ミキハウスのアイテムをもっと身近に」をコンセプトに、 子ども から 大人 、きょうだい、ファミリーで楽しめる、人気の ロゴ アイテムが、デイリーなプライスで登場です。一枚でも着られて、 インナー としても着まわせて便利です。胸元の赤い ミキハウス の ロゴ がアクセントになった ミキハウス ボーダー 半袖Tシャツ です。やわらかくて吸湿性のよい 綿100％ の 天竺 素材の mikihouse 半袖Ｔシャツ は、 WEB LIMITED シリーズのアイテムとコーディネートもおすすめです。着こなしの幅が広がる グレー の ボーダー は新鮮な配色で、今トレンドのニュアンスカラーの配色の マルチ ボーダー にも注目の ミキハウス ボーダー 半袖Ｔシャツ です。● 80cm ・ 90cm 肩あき",
    "aplus_text": "ブランド紹介\n子どもと家族の毎日を笑顔でいっぱいに\n \nおすすめアイテム\n\nストアにアクセス\n\n \nミキハウスロゴグッズ\n\n人気のミキハウスロゴシリーズの雑貨\n\nカラバリ豊富に、コーディネートのポイントに\n\n \n\n私たちミキハウスは、\n\n子どものことを考えた\n\nものづくりとサービスをとおして、\n\n子どもを笑顔にし、家族を笑顔にし、\n\n妊娠・出産・子育ての毎日が\n\nハッピーになるお手伝いをしてまいります。",
    "aplus_images": [
      "https://m.media-amazon.com/images/S/aplus-media-library-service-media/f91690ff-3e9b-4fbd-ad16-74a7add74b87.__CR0,0,1464,625_PT0_SX1464_V1___.jpg",
      "https://m.media-amazon.com/images/I/31MOY4p47LL.__AC_SR166,182___.jpg",
      "https://m.media-amazon.com/images/I/31nz6-AeaeL.__AC_SR166,182___.jpg",
      "https://m.media-amazon.com/images/I/31n7v5G1TFL.__AC_SR166,182___.jpg",
      "https://m.media-amazon.com/images/I/31Wnm%2BteLuL.__AC_SR166,182___.jpg",
      "https://m.media-amazon.com/images/S/aplus-media-library-service-media/6c3c2e46-0e0e-41e5-9c51-f669210bceef.__CR0,0,362,453_PT0_SX362_V1___.jpg",
      "https://m.media-amazon.com/images/S/aplus-media-library-service-media/5149c3d7-56dd-46e5-96d2-de78d23fc12b.__CR0,0,315,145_PT0_SX315_V1___.jpg"
    ],
    "brand_story": "ブランド紹介\n子どもと家族の毎日を笑顔でいっぱいに\n \nおすすめアイテム\n\nストアにアクセス\n\n \nミキハウスロゴグッズ\n\n人気のミキハウスロゴシリーズの雑貨\n\nカラバリ豊富に、コーディネートのポイントに\n\n \n\n私たちミキハウスは、\n\n子どものことを考えた\n\nものづくりとサービスをとおして、\n\n子どもを笑顔にし、家族を笑顔にし、\n\n妊娠・出産・子育ての毎日が\n\nハッピーになるお手伝いをしてまいります。"
  },
  "all_image_urls": [
    "https://m.media-amazon.com/images/I/81zH23q+oML._AC_SL1500_.jpg",
    "https://m.media-amazon.com/images/I/91P8-GNxvDL._AC_SL1500_.jpg",
    "https://m.media-amazon.com/images/I/31lIdNNYmVL._AC_.jpg",
    "https://m.media-amazon.com/images/I/71UqeGRrQ-L._AC_SL1500_.jpg",
    "https://m.media-amazon.com/images/I/41qTsTRrCXL._AC_SR38,50_.jpg",
    "https://m.media-amazon.com/images/I/71ujWz3iesL._AC_SL1500_.jpg",
    "https://m.media-amazon.com/images/I/81RLw4QR52L._AC_SL1500_.jpg",
    "https://m.media-amazon.com/images/I/51zJdh7QFJL._AC_SR38,50_.jpg",
    "https://m.media-amazon.com/images/I/41Di-sP4PZL._AC_.jpg",
    "https://m.media-amazon.com/images/I/41cOYs9JoXL._AC_SR38,50_.jpg",
    "https://m.media-amazon.com/images/I/51zJdh7QFJL._AC_.jpg",
    "https://m.media-amazon.com/images/I/41lWh+B11dL._AC_.jpg",
    "https://m.media-amazon.com/images/I/41cOYs9JoXL._AC_.jpg",
    "https://m.media-amazon.com/images/I/41qTsTRrCXL._AC_.jpg",
    "https://m.media-amazon.com/images/I/81JGf9tKyRL._AC_SL1500_.jpg",
    "https://m.media-amazon.com/images/I/41cOYs9JoXL._AC_SL1500_.jpg",
    "https://m.media-amazon.com/images/I/41qTsTRrCXL._AC_SL1500_.jpg",
    "https://m.media-amazon.com/images/I/51zJdh7QFJL._AC_SL1500_.jpg",
    "https://m.media-amazon.com/images/I/31lIdNNYmVL._AC_SL1500_.jpg",
    "https://m.media-amazon.com/images/I/31RrYoj1i1L._AC_SL1500_.jpg",
    "https://m.media-amazon.com/images/I/51MP0rmQOIL._AC_SL1500_.jpg",
    "https://m.media-amazon.com/images/I/41Di-sP4PZL._AC_SL1500_.jpg",
    "https://m.media-amazon.com/images/I/412fMr4FznL._AC_SL1500_.jpg",
    "https://m.media-amazon.com/images/I/61zLAuYNrUL._AC_SL1500_.jpg",
    "https://m.media-amazon.com/images/I/41lWh+B11dL._AC_SL1500_.jpg",
    "https://m.media-amazon.com/images/I/41786CbvPyL._AC_SL1500_.jpg",
    "https://m.media-amazon.com/images/I/51EFF+EmBNL._AC_SL1500_.jpg",
    "https://m.media-amazon.com/images/S/aplus-media-library-service-media/f91690ff-3e9b-4fbd-ad16-74a7add74b87.__CR0,0,1464,625_PT0_SX1464_V1___.jpg",
    "https://m.media-amazon.com/images/I/31MOY4p47LL.__AC_SR166,182___.jpg",
    "https://m.media-amazon.com/images/I/31nz6-AeaeL.__AC_SR166,182___.jpg",
    "https://m.media-amazon.com/images/I/31n7v5G1TFL.__AC_SR166,182___.jpg",
    "https://m.media-amazon.com/images/I/31Wnm%2BteLuL.__AC_SR166,182___.jpg",
    "https://m.media-amazon.com/images/S/aplus-media-library-service-media/6c3c2e46-0e0e-41e5-9c51-f669210bceef.__CR0,0,362,453_PT0_SX362_V1___.jpg",
    "https://m.media-amazon.com/images/S/aplus-media-library-service-media/5149c3d7-56dd-46e5-96d2-de78d23fc12b.__CR0,0,315,145_PT0_SX315_V1___.jpg"
  ],
  "title_kr": "[미키하우스] WEB한정 스트라이프반팔티셔츠 로고 남아 여아 베이비 키즈 아동복 통원 통학 10-5262-147",
  "folder_name": "[미키하우스]_WEB한정_스트라이프반팔티셔츠_로고_남아_여아_베이비_키즈_아동복_통원_통학_10-5262-147"
}